CHANGES
MANIFEST.in
README.rst
setup.py
pdb4qt/__init__.py
pdb4qt.egg-info/PKG-INFO
pdb4qt.egg-info/SOURCES.txt
pdb4qt.egg-info/dependency_links.txt
pdb4qt.egg-info/top_level.txt