Metadata-Version: 1.0
Name: pdb4qt
Version: 0.2
Summary: A set_trace() that works with PyQt4
Home-page: https://github.com/nqnwebs/pdb4qt
Author: Martín Gaitán
Author-email: gaitan@gmail.com
License: UNKNOWN
Platform: UNKNOWN
Classifier: Development Status :: 4 - Beta
Classifier: Environment :: X11 Applications :: Qt
Classifier: Intended Audience :: Developers
Classifier: Natural Language :: English
Classifier: Operating System :: OS Independent
Classifier: Programming Language :: Python
Classifier: Topic :: Desktop Environment
